zdpapi_mysql/__init__.py
zdpapi_mysql/connection.py
zdpapi_mysql/crud.py
zdpapi_mysql/cursors.py
zdpapi_mysql/log.py
zdpapi_mysql/mysql.py
zdpapi_mysql/pymysql/__init__.py
zdpapi_mysql/pymysql/_auth.py
zdpapi_mysql/pymysql/_compat.py
zdpapi_mysql/pymysql/_socketio.py
zdpapi_mysql/pymysql/charset.py
zdpapi_mysql/pymysql/connections.py
zdpapi_mysql/pymysql/constants/__init__.py
zdpapi_mysql/pymysql/constants/CLIENT.py
zdpapi_mysql/pymysql/constants/COMMAND.py
zdpapi_mysql/pymysql/constants/CR.py
zdpapi_mysql/pymysql/constants/ER.py
zdpapi_mysql/pymysql/constants/FIELD_TYPE.py
zdpapi_mysql/pymysql/constants/FLAG.py
zdpapi_mysql/pymysql/constants/SERVER_STATUS.py
zdpapi_mysql/pymysql/converters.py
zdpapi_mysql/pymysql/cursors.py
zdpapi_mysql/pymysql/err.py
zdpapi_mysql/pymysql/optionfile.py
zdpapi_mysql/pymysql/protocol.py
zdpapi_mysql/pymysql/times.py
zdpapi_mysql/pymysql/util.py
zdpapi_mysql/utils.py
zdpapi_mysql-1.0.2.dist-info/LICENSE
zdpapi_mysql-1.0.2.dist-info/WHEEL
zdpapi_mysql-1.0.2.dist-info/METADATA
zdpapi_mysql-1.0.2.dist-info/RECORD
