Metadata-Version: 2.1
Name: zdpapi-mysql
Version: 1.0.2
Summary: 基于异步的快速操作MySQL的组件
Home-page: https://github.com/zhangdapeng520/zdpapi_mysql
License: MIT
Keywords: zapi,mysql,async,zhangdapeng
Author: 张大鹏
Author-email: lxgzhw@163.com
Requires-Python: >=3.8,<4.0
Classifier: License :: OSI Approved :: MIT License
Classifier: Programming Language :: Python :: 3
Classifier: Programming Language :: Python :: 3.8
Classifier: Programming Language :: Python :: 3.9
Project-URL: Documentation, https://github.com/zhangdapeng520/zdpapi_mysql
Project-URL: Repository, https://github.com/zhangdapeng520/zdpapi_mysql
